ephemeral/__init__.py
ephemeral/cli.py
ephemeral/controller.py
ephemeral/display.py
ephemeral/model.py
ephemeral_sh-0.6.1.dist-info/METADATA
ephemeral_sh-0.6.1.dist-info/WHEEL
ephemeral_sh-0.6.1.dist-info/entry_points.txt
ephemeral_sh-0.6.1.dist-info/top_level.txt
ephemeral_sh-0.6.1.dist-info/RECORD
