Metadata-Version: 2.1
Name: ephemeral-sh
Version: 0.6.1
Summary: A one-task tracker in your terminal with a forgetful history
Author-email: Mike Moran <mike@mkmrn.dev>
Project-URL: GitLab, https://gitlab.com/mmoran0032/ephemeral-sh
Requires-Python: >=3.8
Requires-Dist: typer~=0.13
Provides-Extra: dev
Requires-Dist: black; extra == "dev"
Requires-Dist: build; extra == "dev"
Requires-Dist: isort; extra == "dev"
Requires-Dist: mypy; extra == "dev"
Requires-Dist: pytest; extra == "dev"
Requires-Dist: pytest-cov>=4.0.0; extra == "dev"
Requires-Dist: pytest-mock; extra == "dev"
Requires-Dist: pip-tools>=6.0.0; extra == "dev"
Requires-Dist: twine; extra == "dev"
